templatelite/__init__.py
templatelite/templatelite.py
templatelite/version.py
templatelite-0.2.1.1.dist-info/DESCRIPTION.rst
templatelite-0.2.1.1.dist-info/METADATA
templatelite-0.2.1.1.dist-info/RECORD
templatelite-0.2.1.1.dist-info/WHEEL
templatelite-0.2.1.1.dist-info/metadata.json
templatelite-0.2.1.1.dist-info/top_level.txt
