Metadata-Version: 2.0
Name: templatelite
Version: 0.2.1.1
Summary: templatelite: A very lightweight templating system - suitable for simple html and python code
Home-page: http://templatelite.readthedocs.org/en/latest/
Author: Tony Flury
Author-email: anthony.flury@btinternet.com
License: GNU General Public License (GPL)
Keywords: text html templating jinja
Platform: UNKNOWN
Classifier: Development Status :: 5 - Production/Stable
Classifier: Intended Audience :: Developers
Classifier: Topic :: Software Development :: Libraries :: Python Modules
Classifier: License :: OSI Approved :: GNU General Public License (GPL)
Classifier: Programming Language :: Python :: 2.7
Classifier: Programming Language :: Python :: 3.5
Classifier: Programming Language :: Python :: 3.6
Provides-Extra: dev
Provides-Extra: test
Requires-Dist: six
Provides-Extra: dev
Requires-Dist: check-manifest; extra == 'dev'
Provides-Extra: test
Requires-Dist: coverage; extra == 'test'
